crm_nh_grid/__init__.py
crm_nh_grid/crm.py
crm_nh_grid/icrm.py
crm_nh_grid-0.1.0.dist-info/LICENSE
crm_nh_grid-0.1.0.dist-info/METADATA
crm_nh_grid-0.1.0.dist-info/WHEEL
crm_nh_grid-0.1.0.dist-info/RECORD
